ricky_pyutils/__init__.py
ricky_pyutils/blockchain/coinmarketcap/__init__.py
ricky_pyutils/blockchain/coinmarketcap/api/client.py
ricky_pyutils/blockchain/coinmarketcap/api/endpoints.py
ricky_pyutils/blockchain/coinmarketcap/models/__init__.py
ricky_pyutils/blockchain/coinmarketcap/models/response.py
ricky_pyutils/blockchain/coinmarketcap/models/data/data.py
ricky_pyutils/blockchain/coinmarketcap/models/data/data_torename.py
ricky_pyutils/blockchain/coinmarketcap/models/data/platform.py
ricky_pyutils/blockchain/coinmarketcap/models/data/quote.py
ricky_pyutils/blockchain/coinmarketcap/models/data/tag.py
ricky_pyutils/blockchain/coinmarketcap/models/data/types.py
ricky_pyutils/blockchain/coinmarketcap/services/crypto_service.py
ricky_pyutils-0.1.0.dist-info/licenses/LICENSE
ricky_pyutils-0.1.0.dist-info/METADATA
ricky_pyutils-0.1.0.dist-info/WHEEL
ricky_pyutils-0.1.0.dist-info/top_level.txt
ricky_pyutils-0.1.0.dist-info/RECORD
